dnaMD/__init__.py
dnaMD/dnaEY.py
dnaMD/dnaMD.py
dnaMD/main.py
dnaMD/commands/__init__.py
dnaMD/commands/axisCurv.py
dnaMD/commands/globalElasticity.py
dnaMD/commands/globalEnergy.py
dnaMD/commands/histogram.py
dnaMD/commands/localDeformation.py
dnaMD/commands/localElasticity.py
dnaMD/commands/localEnergy.py
dnaMD/commands/saveAsH5.py
dnaMD/commands/vsBPS.py
dnaMD/commands/vsTime.py
dnamd-2.1.3.dist-info/METADATA
dnamd-2.1.3.dist-info/WHEEL
dnamd-2.1.3.dist-info/entry_points.txt
dnamd-2.1.3.dist-info/top_level.txt
dnamd-2.1.3.dist-info/RECORD
