Metadata-Version: 2.4
Name: dnaMD
Version: 2.1.3
Summary: To analyze fluctuations in DNA or RNA structures in molecular dynamics trajectories
Author-email: Rajendra Kumar <rjdkmr@gmail.com>
License: GNU General Public License v3 (GPLv3)
Project-URL: homepage, https://github.com/rjdkmr/do_x3dna
Project-URL: repository, https://github.com/rjdkmr/do_x3dna
Keywords: DNA,MD Simulation,Elastic Properties,DNA Analysis MD Simulations
Classifier: Environment :: Console
Classifier: Intended Audience :: Developers
Classifier: Intended Audience :: End Users/Desktop
Classifier: Intended Audience :: Science/Research
Classifier: License :: OSI Approved :: GNU General Public License v3 (GPLv3)
Classifier: Natural Language :: English
Classifier: Operating System :: MacOS
Classifier: Operating System :: POSIX :: Linux
Classifier: Topic :: Scientific/Engineering :: Bio-Informatics
Requires-Dist: h5py==3.13.0
Requires-Dist: numpy==2.2.3
Requires-Dist: scipy==1.15.2
Requires-Dist: matplotlib==3.10.0
